{
  "materials": [
    {
      "name": "UiO-66",
      "synthesis_conditions": [
        {
          "temperature": "408 K",
          "solvents": [
            "N,N-diethylformamide (DEF)",
            "formic acid"
          ],
          "solvent_ratio": "1:1 by volume",
          "equipment": "oven",
          "chemicals_used": [
            "ZrOCl2·8 H2O (0.037 mmol)",
            "H2BDC (0.03 mmol)"
          ],
          "time": "2 days",
          "additional_information": "This synthesis condition could be extended to a variety of zirconium salts and functionalized linkers including ZrCl4, ZrBr4, Zr(OPr)4, H2BDC-Br, H2BDC-NH2, H2BDC-NO2, and H2BDC-Me2."
        }
      ]
    }
  ]
}
