{
  "materials": [
    {
      "material": "[Co(PhCOO)2]n (Ia)",
      "conditions": {
        "chemicals_used": "Co(NO3)2·6H2O (582 mg, 2 mmol), benzaldehyde (5 mL)",
        "temperature": "Heated during 10 min",
        "solvents": "Toluene (5 mL) added after cooling",
        "equipment": null,
        "time": "Several hours for crystal formation",
        "washing_method": "Washed with toluene",
        "drying_method": "Dried in a vacuum",
        "yield": "566 mg (94%, based on Co)"
      }
    },
    {
      "material": "[Co(PhCOO)2]n (Ib)",
      "conditions": {
        "chemicals_used": "Co(NO3)2·6H2O (582 mg, 2 mmol), benzaldehyde (5 mL)",
        "temperature": "Heated during 10 min, toluene added to boiling solution",
        "solvents": "Toluene",
        "equipment": null,
        "time": "After cooling for crystal formation",
        "washing_method": "Washed with toluene",
        "drying_method": "Dried in a vacuum",
        "yield": "554 mg (92%, based on Co)"
      }
    },
    {
      "material": "[Co3(PhCOO)6(py)2] (II)",
      "conditions": {
        "chemicals_used": "Co(NO3)2·6H2O (582 mg, 2 mmol), benzaldehyde (5 mL), pyridine (0.2 mL, ∼2 mmol)",
        "temperature": "Heated to boiling during 10 min, then further heated for 5 min after pyridine addition",
        "solvents": "Acetonitrile (0.2 mL) added at 80 °C",
        "equipment": null,
        "time": "Left overnight for crystal formation",
        "washing_method": "Washed with acetonitrile followed by a small amount of pyridine",
        "drying_method": "Air-dried",
        "yield": "0.502 g (71%)"
      }
    },
    {
      "material": "[Co6(OH)2(PhCOO)10(PhCOOH)4]·3PhCH3 (III·3PhCH3)",
      "conditions": {
        "chemicals_used": "Co(NO3)2·6H2O (400 mg, 1.37 mmol), benzaldehyde (10 mL)",
        "temperature": "Heated to boiling during 10 min",
        "solvents": "Toluene (10 mL) added after cooling, water (2 mL) layered",
        "equipment": null,
        "time": "Left undisturbed for 1 month",
        "washing_method": "Washed with toluene",
        "drying_method": "Air-dried",
        "yield": "0.152 g (28%)"
      }
    },
    {
      "material": "[Co8O4(PhCOO)12(CH3CN)3(H2O)]·2CH3CN (IV·2CH3CN)",
      "conditions": {
        "chemicals_used": "Co(NO3)2·6H2O (582 mg, 2 mmol), benzaldehyde (10 mL)",
        "temperature": "Heated to boiling for 10 min",
        "solvents": "Acetonitrile (10 mL) added after cooling, ether (10 mL) and hexane (20 mL) added later",
        "equipment": null,
        "time": "Left undisturbed on air for 1 h, then slowly evaporated",
        "washing_method": "Washed with acetonitrile",
        "drying_method": "Air-dried",
        "yield": "0.275 g (49%, based on Co)"
      }
    },
    {
      "material": "[Ni2Mn(PhCOO)6(py)4]·2CH3CN (V·2CH3CN)",
      "conditions": {
        "chemicals_used": "Ni(NO3)2·6H2O (582 mg, 2 mmol), Mn(NO3)2·6H2O (287 mg, 1 mmol)",
        "temperature": "Similar to II",
        "solvents": "Similar to II",
        "equipment": null,
        "time": "Similar to II",
        "washing_method": "Similar to II",
        "drying_method": "Similar to II",
        "yield": "0.597 g (46%, based on Mn)"
      }
    },
    {
      "material": "[Co2Ni4(OH)2(PhCOO)10(PhCOOH)4] (VI)",
      "conditions": {
        "chemicals_used": "Ni(NO3)2·6H2O (1.16 g, 4 mmol), Co(NO3)2·6H2O (582 mg, 2 mmol)",
        "temperature": "Similar to III",
        "solvents": "Similar to III",
        "equipment": null,
        "time": "Similar to III",
        "washing_method": "Similar to III",
        "drying_method": "Similar to III",
        "yield": "0.668 g (16%, based on Co)"
      }
    },
    {
      "material": "[CoMn(PhCOO)4]n (VII)",
      "conditions": {
        "chemicals_used": "Co(NO3)2·6H2O (582 mg, 2 mmol), Mn(NO3)2·6H2O (574 mg, 2 mmol), benzaldehyde (5 mL)",
        "temperature": "Heated until a precipitate appears",
        "solvents": "Toluene (5 mL) added after cooling",
        "equipment": null,
        "time": "After 1 h for crystal formation",
        "washing_method": "Washed with toluene and ether",
        "drying_method": "Air-dried",
        "yield": "1080 mg (90%, based on Co)"
      }
    },
    {
      "material": "[Co(p-MePhCOO)2]n (VIII)",
      "conditions": {
        "chemicals_used": "Co(NO3)2·6H2O (582 mg, 2 mmol), p-methylbenzaldehyde (5 mL)",
        "temperature": "Heated until the beginning of crystallization",
        "solvents": "Toluene (5 mL) added after cooling",
        "equipment": null,
        "time": "After cooling for crystal formation",
        "washing_method": "Washed with toluene",
        "drying_method": "Dried in a vacuum",
        "yield": "608 mg (92%, based on Co)"
      }
    }
  ]
}
