{
  "materials": [
    {
      "name": "Na(H3B-NH2-BH3)(thf)x",
      "synthesis_conditions": {
        "temperature": "room temperature, then heated to reflux",
        "solvents": [
          {
            "name": "tetrahydrofuran",
            "amount": "150 mL"
          }
        ],
        "equipment": "Schlenk techniques",
        "chemicals_used": [
          {
            "name": "NH3·BH3",
            "amount": "3.00 g, 97.1 mmol"
          },
          {
            "name": "sodium cubes",
            "amount": "20 g, 0.9 mol"
          }
        ],
        "time": "18 h at room temperature, then 21 h at reflux",
        "washing_method": "washed with benzene (2 x 40 mL) and pentane (3 x 30 mL)",
        "drying_method": "evaporated to dryness under vacuum",
        "yield": "1.03 g (28 %)"
      }
    },
    {
      "name": "Na(H3B-NH2-BH3)(thf)x",
      "synthesis_conditions": {
        "temperature": "room temperature, then heated to reflux",
        "solvents": [
          {
            "name": "tetrahydrofuran",
            "amount": "150 mL"
          }
        ],
        "equipment": "Schlenk techniques",
        "chemicals_used": [
          {
            "name": "NH3·BH3",
            "amount": "3.14 g, 102 mmol"
          },
          {
            "name": "NaNH2",
            "amount": "1.95 g, 50.0 mmol"
          }
        ],
        "time": "18 h at room temperature, then 39 h at reflux",
        "washing_method": "washed with benzene (40 mL), diethyl ether (2 x 25 mL), and pentane (2 x 40 mL)",
        "drying_method": "dried under vacuum for 12 h",
        "yield": "1.69 g (50%)"
      }
    },
    {
      "name": "Na(H3B-NMeH-BH3)",
      "synthesis_conditions": {
        "temperature": "0 °C, then heated to reflux",
        "solvents": [
          {
            "name": "tetrahydrofuran",
            "amount": "100 mL of a 1.0 M solution"
          }
        ],
        "equipment": "Schlenk techniques",
        "chemicals_used": [
          {
            "name": "MeNH2",
            "amount": "50 mL of a 2.0 M solution in tetrahydrofuran"
          },
          {
            "name": "sodium cubes",
            "amount": "20 g, 0.9 mol"
          }
        ],
        "time": "stirred for 1 h at 0 °C, then refluxed for 70 h",
        "washing_method": "washed with benzene (3 x 50 mL) and pentane (3 x 75 mL)",
        "drying_method": "dried under vacuum for 40 h",
        "yield": "3.32 g (82 %)"
      }
    },
    {
      "name": "Na(H3B-NEtH-BH3)",
      "synthesis_conditions": {
        "temperature": "0 °C, then heated to reflux",
        "solvents": [
          {
            "name": "tetrahydrofuran",
            "amount": "100 mL of a 1.0 M solution"
          }
        ],
        "equipment": "Schlenk techniques",
        "chemicals_used": [
          {
            "name": "EtNH2",
            "amount": "50 mL of a 2.0 M solution in tetrahydrofuran"
          },
          {
            "name": "sodium cubes",
            "amount": "20 g, 0.9 mol"
          }
        ],
        "time": "stirred for 1 h at 0 °C, then refluxed for 65 h",
        "washing_method": "washed with benzene (2 x 50 mL) and pentane (3 x 50 mL)",
        "drying_method": "dried under vacuum for 20 h",
        "yield": "3.21 g (68 %)"
      }
    },
    {
      "name": "Na(H3B-NMeEt-BH3)",
      "synthesis_conditions": {
        "temperature": "0 °C, then heated to reflux",
        "solvents": [
          {
            "name": "tetrahydrofuran",
            "amount": "100 mL of a 1.0 M solution"
          }
        ],
        "equipment": "Schlenk techniques",
        "chemicals_used": [
          {
            "name": "EtMeNH",
            "amount": "9.0 mL, 0.10 mol"
          },
          {
            "name": "sodium cubes",
            "amount": "30 g, 1.3 mol"
          }
        ],
        "time": "stirred for 1 h at 0 °C, then refluxed for 36 h",
        "washing_method": "washed with benzene (2 x 50 mL) and pentane (2 x 50 mL)",
        "drying_method": "dried under vacuum",
        "yield": "3.70 g (68 %)"
      }
    },
    {
      "name": "Na[H3B-N(C4H8)-BH3]",
      "synthesis_conditions": {
        "temperature": "0 °C, then heated to reflux",
        "solvents": [
          {
            "name": "tetrahydrofuran",
            "amount": "100 mL of a 1.0 M solution"
          }
        ],
        "equipment": "Schlenk techniques",
        "chemicals_used": [
          {
            "name": "pyrrolidine",
            "amount": "8.3 mL, 0.10 mol"
          },
          {
            "name": "sodium cubes",
            "amount": "20 g, 0.9 mol"
          }
        ],
        "time": "stirred for 2 h at 0 °C, then refluxed for 36 h",
        "washing_method": "washed with benzene (2 x 75 mL) and pentane (2 x 75 mL)",
        "drying_method": "dried under vacuum",
        "yield": "4.27 g (71 %)"
      }
    },
    {
      "name": "Na[H3B-N(C5H10)-BH3]",
      "synthesis_conditions": {
        "temperature": "0 °C, then heated to reflux",
        "solvents": [
          {
            "name": "tetrahydrofuran",
            "amount": "200 mL of a 1.0 M solution"
          }
        ],
        "equipment": "Schlenk techniques",
        "chemicals_used": [
          {
            "name": "piperidine",
            "amount": "22 mL, 0.22 mol"
          },
          {
            "name": "sodium cubes",
            "amount": "20 g, 0.9 mol"
          }
        ],
        "time": "stirred for 2 h at 0 °C, then refluxed for 60 h",
        "washing_method": "washed with benzene (80 mL) and pentane (2 x 60 mL)",
        "drying_method": "dried under vacuum",
        "yield": "4.23 g (38 %)"
      }
    },
    {
      "name": "Na(H3B-NMeH-BH3)(1,4-dioxane)0.5",
      "synthesis_conditions": {
        "solvents": [
          {
            "name": "1,4-dioxane",
            "amount": "2 mL"
          }
        ],
        "equipment": "Schlenk techniques",
        "chemicals_used": [
          {
            "name": "Na(H3B-NMeH-BH3)",
            "amount": "100 mg, 1.24 mmol"
          }
        ],
        "time": "stirred for 10 min",
        "washing_method": "extracted with Et2O (50 mL)",
        "drying_method": "evaporated to dryness under vacuum",
        "yield": "colorless prisms"
      }
    },
    {
      "name": "Na(H3B-NEtH-BH3)(1,4-dioxane)",
      "synthesis_conditions": {
        "solvents": [
          {
            "name": "1,4-dioxane",
            "amount": "4 mL"
          }
        ],
        "equipment": "Schlenk techniques",
        "chemicals_used": [
          {
            "name": "Na(H3B-NEtH-BH3)",
            "amount": "100 mg, 1.06 mmol"
          }
        ],
        "time": "stirred for 10 min",
        "washing_method": "extracted with Et2O (35 mL)",
        "drying_method": "evaporated to dryness under vacuum",
        "yield": "colorless prisms"
      }
    },
    {
      "name": "Na[H3B-N(C4H8)-BH3](1,4-dioxane)",
      "synthesis_conditions": {
        "solvents": [
          {
            "name": "1,4-dioxane",
            "amount": "4 mL"
          }
        ],
        "equipment": "Schlenk techniques",
        "chemicals_used": [
          {
            "name": "Na[H3B-N(C4H8)-BH3]",
            "amount": "100 mg, 0.83 mmol"
          }
        ],
        "time": "stirred for 10 min",
        "washing_method": "extracted with Et2O (35 mL)",
        "drying_method": "evaporated to dryness under vacuum",
        "yield": "colorless prisms"
      }
    },
    {
      "name": "Er(H3B-NH2-BH3)Cl2(thf)3",
      "synthesis_conditions": {
        "temperature": "0 °C, then room temperature",
        "solvents": [
          {
            "name": "tetrahydrofuran",
            "amount": "30 mL"
          }
        ],
        "equipment": "Schlenk techniques",
        "chemicals_used": [
          {
            "name": "ErCl3",
            "amount": "0.30 g, 1.1 mmol"
          },
          {
            "name": "Na(H3B-NH2-BH3)",
            "amount": "0.23 g, 3.5 mmol"
          }
        ],
        "time": "stirred for 24 h",
        "washing_method": "filtered",
        "drying_method": "dynamic vacuum overnight",
        "yield": "0.24 g (41 %)"
      }
    }
  ]
}
