{
  "materials": [
    {
      "material": "Eu-1,4-NDC-fcu-MOF",
      "synthesis_conditions": {
        "temperature": "115 °C",
        "solvents": [
          {
            "name": "DMF",
            "amount": "2.2 mL"
          },
          {
            "name": "H2O",
            "amount": "0.5 mL"
          }
        ],
        "equipment": "20 mL scintillation vial",
        "chemicals_used": [
          {
            "name": "1,4-H2NDC",
            "amount": "9.41 mg"
          },
          {
            "name": "Eu(NO3)3·5H2O",
            "amount": "18.6 mg"
          },
          {
            "name": "2-fluorobenzoic acid",
            "amount": "48.7 mg"
          },
          {
            "name": "HNO3",
            "amount": "0.3 mL, 3.5 M in DMF"
          }
        ],
        "time": "60 h",
        "drying_method": "air-dried",
        "yield": "Not specified",
        "washing_method": "Not specified"
      }
    },
    {
      "material": "Tb-1,4-NDC-fcu-MOF",
      "synthesis_conditions": {
        "temperature": "115 °C",
        "solvents": [
          {
            "name": "DMF",
            "amount": "2.2 mL"
          },
          {
            "name": "H2O",
            "amount": "0.5 mL"
          }
        ],
        "equipment": "20 mL scintillation vial",
        "chemicals_used": [
          {
            "name": "1,4-H2NDC",
            "amount": "9.42 mg"
          },
          {
            "name": "Tb(NO3)3·5H2O",
            "amount": "18.9 mg"
          },
          {
            "name": "2-fluorobenzoic acid",
            "amount": "48.7 mg"
          },
          {
            "name": "HNO3",
            "amount": "0.3 mL, 3.5 M in DMF"
          }
        ],
        "time": "60 h",
        "drying_method": "air-dried",
        "yield": "Not specified",
        "washing_method": "Not specified"
      }
    },
    {
      "material": "Y-1,4-NDC-fcu-MOF",
      "synthesis_conditions": {
        "temperature": "115 °C",
        "solvents": [
          {
            "name": "DMF",
            "amount": "2.2 mL"
          },
          {
            "name": "H2O",
            "amount": "0.5 mL"
          }
        ],
        "equipment": "20 mL scintillation vial",
        "chemicals_used": [
          {
            "name": "1,4-H2NDC",
            "amount": "9.40 mg"
          },
          {
            "name": "Y(NO3)3·6H2O",
            "amount": "16.7 mg"
          },
          {
            "name": "2-fluorobenzoic acid",
            "amount": "48.7 mg"
          },
          {
            "name": "HNO3",
            "amount": "0.3 mL, 3.5 M in DMF"
          }
        ],
        "time": "60 h",
        "drying_method": "air-dried",
        "yield": "Not specified",
        "washing_method": "Not specified"
      }
    }
  ]
}
